snipssonos/Snipsspec
snipssonos/__init__.py
snipssonos/snipssonos.py
snipssonos/spotify.py
snipssonos-1.0.0.dist-info/DESCRIPTION.rst
snipssonos-1.0.0.dist-info/METADATA
snipssonos-1.0.0.dist-info/RECORD
snipssonos-1.0.0.dist-info/WHEEL
snipssonos-1.0.0.dist-info/metadata.json
snipssonos-1.0.0.dist-info/top_level.txt
