Metadata-Version: 2.0
Name: snipssonos
Version: 1.0.0
Summary: Sonos skill for Snips
Home-page: https://github.com/snipsco/snips-skill-sonos
Author: The Als
Author-email: UNKNOWN
License: MIT
Keywords: snips,sonos
Platform: UNKNOWN
Requires-Dist: soco
